aiohttp/__init__.py
aiohttp/abc.py
aiohttp/base_protocol.py
aiohttp/client.py
aiohttp/client_exceptions.py
aiohttp/client_proto.py
aiohttp/client_reqrep.py
aiohttp/client_ws.py
aiohttp/connector.py
aiohttp/cookiejar.py
aiohttp/formdata.py
aiohttp/hdrs.py
aiohttp/helpers.py
aiohttp/http.py
aiohttp/http_exceptions.py
aiohttp/http_parser.py
aiohttp/http_websocket.py
aiohttp/http_writer.py
aiohttp/locks.py
aiohttp/log.py
aiohttp/multipart.py
aiohttp/payload.py
aiohttp/payload_streamer.py
aiohttp/pytest_plugin.py
aiohttp/resolver.py
aiohttp/streams.py
aiohttp/tcp_helpers.py
aiohttp/test_utils.py
aiohttp/tracing.py
aiohttp/typedefs.py
aiohttp/web.py
aiohttp/web_app.py
aiohttp/web_exceptions.py
aiohttp/web_fileresponse.py
aiohttp/web_log.py
aiohttp/web_middlewares.py
aiohttp/web_protocol.py
aiohttp/web_request.py
aiohttp/web_response.py
aiohttp/web_routedef.py
aiohttp/web_runner.py
aiohttp/web_server.py
aiohttp/web_urldispatcher.py
aiohttp/web_ws.py
aiohttp/worker.py
aiosignal/__init__.py
async_timeout/__init__.py
attr/__init__.py
attr/_cmp.py
attr/_compat.py
attr/_config.py
attr/_funcs.py
attr/_make.py
attr/_next_gen.py
attr/_version_info.py
attr/converters.py
attr/exceptions.py
attr/filters.py
attr/setters.py
attr/validators.py
attrs/__init__.py
attrs/converters.py
attrs/exceptions.py
attrs/filters.py
attrs/setters.py
attrs/validators.py
bidict/__init__.py
bidict/_abc.py
bidict/_base.py
bidict/_bidict.py
bidict/_dup.py
bidict/_exc.py
bidict/_frozenbidict.py
bidict/_frozenordered.py
bidict/_iter.py
bidict/_named.py
bidict/_orderedbase.py
bidict/_orderedbidict.py
bidict/_typing.py
bidict/metadata.py
certifi/__init__.py
certifi/__main__.py
certifi/core.py
charset_normalizer/__init__.py
charset_normalizer/__main__.py
charset_normalizer/api.py
charset_normalizer/cd.py
charset_normalizer/constant.py
charset_normalizer/legacy.py
charset_normalizer/md.py
charset_normalizer/models.py
charset_normalizer/utils.py
charset_normalizer/version.py
charset_normalizer/cli/__init__.py
lambda_tago-0.1.0.dist-info/METADATA
lambda_tago-0.1.0.dist-info/WHEEL
lambda_tago-0.1.0.dist-info/top_level.txt
lambda_tago-0.1.0.dist-info/RECORD
