Metadata-Version: 2.1
Name: lambda-tago
Version: 0.1.0
Summary: A custom library for interacting with Tago
Home-page: UNKNOWN
Author: Vincent Raaijmakers
Author-email: UNKNOWN
License: UNKNOWN
Platform: UNKNOWN
